dashboard_agent/__init__.py
dashboard_agent/agent.py
dashboard_agent/server.py
dashboard_agent-0.1.0.dist-info/METADATA
dashboard_agent-0.1.0.dist-info/WHEEL
dashboard_agent-0.1.0.dist-info/entry_points.txt
dashboard_agent-0.1.0.dist-info/top_level.txt
dashboard_agent-0.1.0.dist-info/RECORD
